py_auth_header_parser/__init__.py
py_auth_header_parser/parser.py
py_auth_header_parser-1.0.2.dist-info/LICENSE
py_auth_header_parser-1.0.2.dist-info/METADATA
py_auth_header_parser-1.0.2.dist-info/WHEEL
py_auth_header_parser-1.0.2.dist-info/top_level.txt
py_auth_header_parser-1.0.2.dist-info/RECORD
