Metadata-Version: 2.1
Name: py-auth-header-parser
Version: 1.0.2
Summary: Small and simple Python library to parse JWT tokens embedded in http auth. headers.
Home-page: https://github.com/cgons/py-auth-header-parser
Author: Chrys Gonsalves
Author-email: cgons@pcxchange.ca
License: UNKNOWN
Platform: UNKNOWN
Classifier: Programming Language :: Python :: 3
Classifier: License :: OSI Approved :: MIT License
Classifier: Operating System :: OS Independent
Requires-Python: >=3.5
Provides-Extra: dev
Requires-Dist: pytest ; extra == 'dev'
Requires-Dist: wheel ; extra == 'dev'
